summarix/__init__.py
summarix/main.py
summarix/prompts.py
summarix-2025.12.21123439.dist-info/METADATA
summarix-2025.12.21123439.dist-info/WHEEL
summarix-2025.12.21123439.dist-info/top_level.txt
summarix-2025.12.21123439.dist-info/RECORD
