Metadata-Version: 2.4
Name: summarix
Version: 2025.12.21123439
Summary: A new package designed to process user-inputted text statements or stories and extract structured summaries or insights using a reliable language model with pattern matching and retries. It simplifies
Author-email: summarix <hi@eugene.plus>
License: MIT
Project-URL: Homepage, https://github.com/chigwell/summarix
Requires-Python: >=3.9
Requires-Dist: langchain-llm7>=0.0.0
Requires-Dist: llmatch-messages>=0.0.0
Requires-Dist: langchain-core>=0.3.0
